thzsts.py
thzsts-0.0.3.dist-info/LICENSE.txt
thzsts-0.0.3.dist-info/METADATA
thzsts-0.0.3.dist-info/WHEEL
thzsts-0.0.3.dist-info/top_level.txt
thzsts-0.0.3.dist-info/RECORD
