Metadata-Version: 2.1
Name: thzsts
Version: 0.0.3
Summary: Function to perform THz STS algorithm and simulate measurements.
Home-page: https://github.com/NanoTHzCoding/THz_STS_Algorithm
Author: Stefanie Adams
Author-email: nanothz.coding@gmail.com
Classifier: Programming Language :: Python :: 3
Classifier: License :: OSI Approved :: MIT License
License-File: LICENSE.txt
Requires-Dist: numpy
Requires-Dist: scipy
Requires-Dist: matplotlib
Requires-Dist: scikit-learn
